lab2/Booth.sv
// Generated by CIRCT firtool-1.62.0
module Booth(
  input         clock,
                reset,
                io_start,
  input  [31:0] io_x,
                io_y,
  output [63:0] io_z,
  output        io_busy
);

  reg        state;
  reg        busy;
  reg [31:0] _x;
  reg [31:0] _y;
  reg [63:0] _z;
  reg [4:0]  cnt_value;
  always @(posedge clock) begin
    if (reset) begin
      state <= 1'h0;
      busy <= 1'h0;
      _x <= 32'h0;
      _y <= 32'h0;
      _z <= 64'h0;
      cnt_value <= 5'h0;
    end
    else begin
      if (state) begin
        automatic logic [4:0] _q_T_1;
        _q_T_1 = cnt_value + 5'h1;
        state <= ~(&cnt_value);
        busy <= ~(&cnt_value);
        if (~state | (&cnt_value)) begin
        end
        else begin
          automatic logic [31:0] _q_T_5 = _y >> cnt_value;
          automatic logic [31:0] _q_T_3;
          automatic logic [1:0]  _q_1;
          _q_T_3 = _y >> _q_T_1;
          _q_1 = {_q_T_3[0], _q_T_5[0]};
          if (_q_1 == 2'h0 | (&_q_1))
            _z <= {_z[63], _z[63:1]};
          else begin
            automatic logic [63:0] _GEN;
            _GEN = {_x, 32'h0};
            if (_q_1 == 2'h1) begin
              automatic logic [63:0] __z_T_3;
              __z_T_3 = _z + _GEN;
              _z <= {__z_T_3[63], __z_T_3[63:1]};
            end
            else if (_q_1 == 2'h2) begin
              automatic logic [63:0] __z_T_5;
              __z_T_5 = _z - _GEN;
              _z <= {__z_T_5[63], __z_T_5[63:1]};
            end
          end
        end
        cnt_value <= _q_T_1;
      end
      else begin
        state <= io_start | state;
        busy <= io_start | busy;
        if (io_start) begin
          automatic logic [31:0] __z_T_1 = 32'h0 - io_x;
          _z <= io_y[0] ? {__z_T_1[31], __z_T_1, 31'h0} : 64'h0;
        end
      end
      if (~state & io_start) begin
        _x <= io_x;
        _y <= io_y;
      end
    end
  end // always @(posedge)
  assign io_z = _z;
  assign io_busy = busy;
endmodule

lab2/Booth.vcd
$version Generated by VerilatedVcd $end
$timescale 1ps $end
 $scope module TOP $end
  $var wire 1 & clock $end
  $var wire 1 ' reset $end
  $var wire 1 ( io_start $end
  $var wire 32 ) io_x [31:0] $end
  $var wire 32 * io_y [31:0] $end
  $var wire 64 + io_z [63:0] $end
  $var wire 1 - io_busy $end
  $scope module Booth $end
   $var wire 1 & clock $end
   $var wire 1 ' reset $end
   $var wire 1 ( io_start $end
   $var wire 32 ) io_x [31:0] $end
   $var wire 32 * io_y [31:0] $end
   $var wire 64 + io_z [63:0] $end
   $var wire 1 - io_busy $end
   $var wire 1 # state $end
   $var wire 1 $ busy $end
   $var wire 5 % cnt_value [4:0] $end
  $upscope $end
 $upscope $end
$enddefinitions $end


#0
0#
0$
b00000 %
1&
1'
0(
b00000000000000000000000000000000 )
b00000000000000000000000000000000 *
b0000000000000000000000000000000000000000000000000000000000000000 +
0-
#10
0&
#20
1&
#30
0&
#40
1&
#45
0'
b00000000000000000000000001111101 )
b11111111111111111111111110010000 *
#50
0&
#55
1#
1$
1&
1(
1-
#60
0&
#65
b00001 %
1&
0(
#70
0&
#75
b00010 %
1&
#80
0&
#85
b00011 %
1&
#90
0&
#95
b00100 %
1&
b1111111111111111111111111100000110000000000000000000000000000000 +
#100
0&
#105
b00101 %
1&
b0000000000000000000000000001111101000000000000000000000000000000 +
#110
0&
#115
b00110 %
1&
b0000000000000000000000000000111110100000000000000000000000000000 +
#120
0&
#125
b00111 %
1&
b1111111111111111111111111100100101010000000000000000000000000000 +
#130
0&
#135
b01000 %
1&
b1111111111111111111111111110010010101000000000000000000000000000 +
#140
0&
#145
b01001 %
1&
b1111111111111111111111111111001001010100000000000000000000000000 +
#150
0&
#155
b01010 %
1&
b1111111111111111111111111111100100101010000000000000000000000000 +
#160
0&
#165
b01011 %
1&
b1111111111111111111111111111110010010101000000000000000000000000 +
#170
0&
#175
b01100 %
1&
b1111111111111111111111111111111001001010100000000000000000000000 +
#180
0&
#185
b01101 %
1&
b1111111111111111111111111111111100100101010000000000000000000000 +
#190
0&
#195
b01110 %
1&
b1111111111111111111111111111111110010010101000000000000000000000 +
#200
0&
#205
b01111 %
1&
b1111111111111111111111111111111111001001010100000000000000000000 +
#210
0&
#215
b10000 %
1&
b1111111111111111111111111111111111100100101010000000000000000000 +
#220
0&
#225
b10001 %
1&
b1111111111111111111111111111111111110010010101000000000000000000 +
#230
0&
#235
b10010 %
1&
b1111111111111111111111111111111111111001001010100000000000000000 +
#240
0&
#245
b10011 %
1&
b1111111111111111111111111111111111111100100101010000000000000000 +
#250
0&
#255
b10100 %
1&
b1111111111111111111111111111111111111110010010101000000000000000 +
#260
0&
#265
b10101 %
1&
b1111111111111111111111111111111111111111001001010100000000000000 +
#270
0&
#275
b10110 %
1&
b1111111111111111111111111111111111111111100100101010000000000000 +
#280
0&
#285
b10111 %
1&
b1111111111111111111111111111111111111111110010010101000000000000 +
#290
0&
#295
b11000 %
1&
b1111111111111111111111111111111111111111111001001010100000000000 +
#300
0&
#305
b11001 %
1&
b1111111111111111111111111111111111111111111100100101010000000000 +
#310
0&
#315
b11010 %
1&
b1111111111111111111111111111111111111111111110010010101000000000 +
#320
0&
#325
b11011 %
1&
b1111111111111111111111111111111111111111111111001001010100000000 +
#330
0&
#335
b11100 %
1&
b1111111111111111111111111111111111111111111111100100101010000000 +
#340
0&
#345
b11101 %
1&
b1111111111111111111111111111111111111111111111110010010101000000 +
#350
0&
#355
b11110 %
1&
b1111111111111111111111111111111111111111111111111001001010100000 +
#360
0&
#365
b11111 %
1&
b1111111111111111111111111111111111111111111111111100100101010000 +
#370
0&
#375
0#
0$
b00000 %
1&
0-
