lab2/Booth.sv
// Generated by CIRCT firtool-1.62.0
module Booth(
  input         clock,
                reset,
                io_start,
  input  [7:0]  io_x,
                io_y,
  output [15:0] io_z,
  output        io_busy
);

  reg        state;
  reg        busy;
  reg [7:0]  _x;
  reg [7:0]  _y;
  reg [15:0] _z;
  reg [2:0]  cnt_value;
  always @(posedge clock) begin
    if (reset) begin
      state <= 1'h0;
      busy <= 1'h0;
      _x <= 8'h0;
      _y <= 8'h0;
      _z <= 16'h0;
      cnt_value <= 3'h0;
    end
    else begin
      automatic logic [15:0] _GEN;
      _GEN = {_z[15], _z[15:1]};
      if (state) begin
        automatic logic [2:0] _q_T_1;
        _q_T_1 = cnt_value + 3'h1;
        state <= ~(&cnt_value);
        busy <= ~(&cnt_value);
        if (~state | (&cnt_value)) begin
        end
        else begin
          automatic logic [7:0] _q_T_5 = $signed($signed(_y) >>> cnt_value);
          automatic logic [7:0] _q_T_3;
          automatic logic [1:0] _q_1;
          _q_T_3 = $signed($signed(_y) >>> _q_T_1);
          _q_1 = {_q_T_3[0], _q_T_5[0]};
          if (_q_1 == 2'h0 | (&_q_1))
            _z <= _GEN;
          else begin
            automatic logic [15:0] _GEN_0;
            _GEN_0 = {_x, 8'h0};
            if (_q_1 == 2'h1) begin
              automatic logic [15:0] _z_T_16;
              _z_T_16 = _z + _GEN_0;
              _z <= {_z_T_16[15], _z_T_16[15:1]};
            end
            else if (_q_1 == 2'h2) begin
              automatic logic [15:0] _z_T_21;
              _z_T_21 = _z - _GEN_0;
              _z <= {_z_T_21[15], _z_T_21[15:1]};
            end
          end
        end
        cnt_value <= _q_T_1;
      end
      else begin
        state <= io_start | state;
        busy <= io_start | busy;
        if (io_start) begin
          if (io_y[0]) begin
            automatic logic [7:0] _z_T_6 = 8'h0 - io_x;
            _z <= {_z_T_6[7], _z_T_6, io_y[7:1]};
          end
          else
            _z <= _GEN;
        end
      end
      if (~state & io_start) begin
        _x <= io_x;
        _y <= io_y;
      end
    end
  end // always @(posedge)
  assign io_z = _z;
  assign io_busy = busy;
endmodule

lab2/mul.vcd
$version Generated by VerilatedVcd $end
$timescale 1ps $end
 $scope module TOP $end
  $var wire 1 & clock $end
  $var wire 1 ' reset $end
  $var wire 1 ( io_start $end
  $var wire 8 ) io_x [7:0] $end
  $var wire 8 * io_y [7:0] $end
  $var wire 16 + io_z [15:0] $end
  $var wire 1 , io_busy $end
  $scope module Booth $end
   $var wire 1 & clock $end
   $var wire 1 ' reset $end
   $var wire 1 ( io_start $end
   $var wire 8 ) io_x [7:0] $end
   $var wire 8 * io_y [7:0] $end
   $var wire 16 + io_z [15:0] $end
   $var wire 1 , io_busy $end
   $var wire 1 # state $end
   $var wire 1 $ busy $end
   $var wire 3 % cnt_value [2:0] $end
  $upscope $end
 $upscope $end
$enddefinitions $end


#0
0#
0$
b000 %
1&
1'
0(
b00000000 )
b00000000 *
b0000000000000000 +
0,
#10
0&
#20
1&
#30
0&
#40
1&
#45
0'
b00111001 )
b00011001 *
#50
0&
#55
1#
1$
1&
1(
b1110001110000000 +
1,
#60
0&
#65
b001 %
1&
0(
b0000111001000000 +
#70
0&
#75
b010 %
1&
b0000011100100000 +
#80
0&
#85
b011 %
1&
b1110011100010000 +
#90
0&
#95
b100 %
1&
b1111001110001000 +
#100
0&
#105
b101 %
1&
b0001011001000100 +
#110
0&
#115
b110 %
1&
b0000101100100010 +
#120
0&
#125
b111 %
1&
b0000010110010001 +
#130
0&
#135
0#
0$
b000 %
1&
0,
